03_finite_state_machines/03_02_detect_sequence_using_shift_reg.sv
//----------------------------------------------------------------------------
// Example
//----------------------------------------------------------------------------

module detect_4_bit_sequence_using_shift_reg
(
  input  clk,
  input  rst,
  input  new_bit,
  output detected
);

  // Detection of the "1010" sequence using shift register

  logic [3:0] shift_reg;

  assign detected =   shift_reg[3] &
                    ~ shift_reg[2] &
                      shift_reg[1] &
                    ~ shift_reg[0];

  always_ff @ (posedge clk)
    if (rst)
      shift_reg <= '0;
    else
      shift_reg <= {shift_reg[2:0], new_bit };

endmodule

//----------------------------------------------------------------------------
// Task
//----------------------------------------------------------------------------

module detect_6_bit_sequence_using_shift_reg
(
  input  clk,
  input  rst,
  input  new_bit,
  output detected
);

  // Detection of the "110011" sequence using shift register

  logic [5:0] shift_reg;

  assign detected =   shift_reg[5] &
                      shift_reg[4] &
                    ~ shift_reg[3] &
                    ~ shift_reg[2] &
                      shift_reg[1] &
                      shift_reg[0];

  always_ff @ (posedge clk)
    if (rst)
      shift_reg <= '0;
    else
      shift_reg <= {shift_reg[4:0], new_bit };    


endmodule

//----------------------------------------------------------------------------
// Testbench
//----------------------------------------------------------------------------

module testbench;

  logic clk;

  initial
  begin
    clk = '0;

    forever
      # 500 clk = ~ clk;
  end

  logic rst;

  initial
  begin
    rst <= 'x;
    repeat (2) @ (posedge clk);
    rst <= '1;
    repeat (2) @ (posedge clk);
    rst <= '0;
  end

  logic new_bit, det4bit, det6bit;
  detect_4_bit_sequence_using_shift_reg det4b (.detected (det4bit),  .*);
  detect_6_bit_sequence_using_shift_reg det6b (.detected (det6bit), .*);

  localparam n = 24;

  // The sequence of input values
  localparam [0 : n - 1] seq_new_bit       = 24'b0011_0101_1001_1001_1010_1000;

  // The sequence of expected output values
  localparam [0 : n - 1] seq_det4bit = 24'b0000_0001_0000_0000_0000_1010;
  localparam [0 : n - 1] seq_det6bit = 24'b0000_0000_0000_0100_0100_0000;

  initial
  begin
    // Remove the comments below to generate the dump.vcd file and analyze it with GTKwave
    // $dumpfile("dump_03_02.vcd");
    // $dumpvars(0, testbench);

    @ (negedge rst);

    for (int i = 0; i < n; i ++)
    begin
      new_bit <= seq_new_bit [i];

      @ (posedge clk);

      $display ("%b %b (%b) %b (%b)",
        new_bit,
        det4bit, seq_det4bit[i],
        det6bit, seq_det6bit[i]);

      if (   det4bit !== seq_det4bit[i]
          || det6bit !== seq_det6bit[i])
      begin
        $display ("%s FAIL - see log above", `__FILE__);
        $finish;
      end
    end

    $display ("%s PASS", `__FILE__);
    $finish;
  end

endmodule

03_finite_state_machines/dump_03_02.vcd
$date
	Thu Nov 16 00:12:57 2023
$end
$version
	Icarus Verilog
$end
$timescale
	1s
$end
$scope module testbench $end
$var wire 1 ! det6bit $end
$var wire 1 " det4bit $end
$var parameter 32 # n $end
$var parameter 24 $ seq_det4bit $end
$var parameter 24 % seq_det6bit $end
$var parameter 24 & seq_new_bit $end
$var reg 1 ' clk $end
$var reg 1 ( new_bit $end
$var reg 1 ) rst $end
$scope module det4b $end
$var wire 1 ' clk $end
$var wire 1 " detected $end
$var wire 1 ( new_bit $end
$var wire 1 ) rst $end
$var reg 4 * shift_reg [3:0] $end
$upscope $end
$scope module det6b $end
$var wire 1 ' clk $end
$var wire 1 ! detected $end
$var wire 1 ( new_bit $end
$var wire 1 ) rst $end
$var reg 6 + shift_reg [5:0] $end
$upscope $end
$scope begin $ivl_for_loop0 $end
$var integer 32 , i [31:0] $end
$upscope $end
$upscope $end
$enddefinitions $end
$comment Show the parameter values. $end
$dumpall
b1101011001100110101000 &
b10001000000 %
b10000000000001010 $
b11000 #
$end
#0
$dumpvars
b0 ,
bx +
bx *
x)
x(
0'
x"
x!
$end
#500
1'
#1000
0'
#1500
1)
1'
#2000
0'
#2500
0"
0!
b0 *
b0 +
1'
#3000
0'
#3500
0(
0)
1'
#4000
0'
#4500
b1 ,
1'
#5000
0'
#5500
1(
b10 ,
1'
#6000
0'
#6500
b1 *
b1 +
b11 ,
1'
#7000
0'
#7500
0(
b11 +
b11 *
b100 ,
1'
#8000
0'
#8500
b110 *
b110 +
1(
b101 ,
1'
#9000
0'
#9500
0(
b1101 +
b1101 *
b110 ,
1'
#10000
0'
#10500
1"
b1010 *
b11010 +
1(
b111 ,
1'
#11000
0'
#11500
0"
b110101 +
b101 *
b1000 ,
1'
#12000
0'
#12500
0!
b1011 *
b101011 +
0(
b1001 ,
1'
#13000
0'
#13500
0"
b10110 +
b110 *
b1010 ,
1'
#14000
0'
#14500
b1100 *
b101100 +
1(
b1011 ,
1'
#15000
0'
#15500
b11001 +
b1001 *
b1100 ,
1'
#16000
0'
#16500
1!
b11 *
b110011 +
0(
b1101 ,
1'
#17000
0'
#17500
0!
b100110 +
b110 *
b1110 ,
1'
#18000
0'
#18500
b1100 *
b1100 +
1(
b1111 ,
1'
#19000
0'
#19500
b11001 +
b1001 *
b10000 ,
1'
#20000
0'
#20500
1!
b11 *
b110011 +
0(
b10001 ,
1'
#21000
0'
#21500
0!
1(
b100110 +
b110 *
b10010 ,
1'
#22000
0'
#22500
b1101 *
b1101 +
0(
b10011 ,
1'
#23000
0'
#23500
1"
1(
b11010 +
b1010 *
b10100 ,
1'
#24000
0'
#24500
0"
b101 *
b110101 +
0(
b10101 ,
1'
#25000
0'
#25500
1"
b101010 +
b1010 *
b10110 ,
1'
#26000
0'
#26500
0"
b100 *
b10100 +
b10111 ,
1'
#27000
0'
#27500
b101000 +
b1000 *
b11000 ,
1'
